pydisadm/__init__.py
pydisadm/__main__.py
pydisadm/bot/__init__.py
pydisadm/bot/adm_bot.py
pydisadm/bot/adm_cog.py
pydisadm/bot/update_adm_modal.py
pydisadm/bot/utils.py
pydisadm/configuration.py
pydisadm/controller/__init__.py
pydisadm/controller/adm_controller.py
pydisadm/data/__init__.py
pydisadm/data/mapConstellations.csv
pydisadm/data/mapRegions.csv
pydisadm/data/mapSolarSystems.csv
pydisadm/loader/__init__.py
pydisadm/loader/datasets.py
pydisadm/loader/static_data.py
pydisadm/runnable/__init__.py
pydisadm/runnable/runnable_refresh.py
pydisadm/services/__init__.py
pydisadm/services/common.py
pydisadm/services/database.py
pydisadm/services/database_mysql.py
pydisadm/services/database_sqlite.py
pydisadm/services/esi.py
pydisadm/services/factory.py
pydisadm/utils/__init__.py
pydisadm/utils/adm_utils.py
pydisadm/utils/datetime_utils.py
pydisadm/utils/plot_utils.py
pydisadm/utils/thread_utils.py
pydisadm-2.2.0.dist-info/METADATA
pydisadm-2.2.0.dist-info/WHEEL
pydisadm-2.2.0.dist-info/RECORD
