Metadata-Version: 2.1
Name: pydisadm
Version: 2.2.0
Summary: A Discord bot providing ADM summaries.
Home-page: https://github.com/agelito/adm-bot
License: MIT
Author: Axel Wettervik
Author-email: axel.wettervik@gmail.com
Requires-Python: >=3.8,<4.0
Classifier: License :: OSI Approved :: MIT License
Classifier: Programming Language :: Python :: 3
Classifier: Programming Language :: Python :: 3.8
Classifier: Programming Language :: Python :: 3.9
Classifier: Programming Language :: Python :: 3.10
Classifier: Programming Language :: Python :: 3.11
Requires-Dist: discord (>=2.2.3,<3.0.0)
Requires-Dist: matplotlib (>=3.7.1,<4.0.0)
Requires-Dist: mysqlclient (>=2.2.0,<3.0.0)
Requires-Dist: pandas (>=2.0.1,<3.0.0)
Requires-Dist: python-dotenv (>=1.0.0,<2.0.0)
Requires-Dist: requests (>=2.30.0,<3.0.0)
Requires-Dist: schedule (>=1.2.0,<2.0.0)
Requires-Dist: sqlalchemy (>=2.0.19,<3.0.0)
Requires-Dist: tabulate (>=0.9.0,<0.10.0)
Project-URL: Repository, https://github.com/agelito/adm-bot
